{
  "generated_at": "2026-07-04T00:01:05.036580+00:00",
  "target_date": "2026-07-01",
  "current_state": {
    "ndx_close": 29809.13,
    "vix": 16.59,
    "tnx": 4.37,
    "tnx_1y_ago": 4.25,
    "tnx_2y_ago": 4.48,
    "tnx_5y_ago": 1.43,
    "tnx_1y_high": 4.67,
    "tnx_1y_low": 3.95,
    "tnx_diff_1y": 0.12,
    "tnx_trend": "보합",
    "rsi14": 59.3,
    "bb_pctb": 54.75,
    "ma_align": 0
  },
  "analysis": {
    "data_period": "2000-12-29 ~ 2026-07-01",
    "total_days": 6412,
    "n_neighbors": 200,
    "n_features": 21,
    "distance_range": [
      2.51,
      3.37
    ]
  },
  "horizons": [
    {
      "horizon_days": 1,
      "horizon_label": "1일 후",
      "up_probability": 60.5,
      "up_count": 121,
      "total_count": 200,
      "direction_label": "상승 우세",
      "direction_icon": "📈",
      "direction_color": "strong-up"
    },
    {
      "horizon_days": 5,
      "horizon_label": "5일 후 (1주)",
      "up_probability": 56.0,
      "up_count": 112,
      "total_count": 200,
      "direction_label": "약한 상승",
      "direction_icon": "↗",
      "direction_color": "weak-up"
    },
    {
      "horizon_days": 20,
      "horizon_label": "20일 후 (1달)",
      "up_probability": 54.5,
      "up_count": 109,
      "total_count": 200,
      "direction_label": "중립",
      "direction_icon": "→",
      "direction_color": "neutral"
    }
  ],
  "top_similar_dates": [
    {
      "date": "2021-12-23",
      "distance": 2.51,
      "close": 16308.21,
      "vix": 17.96,
      "ret_1d": 1.59,
      "ret_5d": 0.07,
      "ret_20d": -11.03
    },
    {
      "date": "2021-12-09",
      "distance": 2.52,
      "close": 16149.57,
      "vix": 21.58,
      "ret_1d": 1.13,
      "ret_5d": -1.77,
      "ret_20d": -3.45
    },
    {
      "date": "2025-11-26",
      "distance": 2.63,
      "close": 25236.94,
      "vix": 17.19,
      "ret_1d": 0.78,
      "ret_5d": 1.37,
      "ret_20d": 1.61
    },
    {
      "date": "2010-11-29",
      "distance": 2.64,
      "close": 2144.56,
      "vix": 21.53,
      "ret_1d": -1.27,
      "ret_5d": 2.11,
      "ret_20d": 3.86
    },
    {
      "date": "2021-12-08",
      "distance": 2.66,
      "close": 16394.34,
      "vix": 19.9,
      "ret_1d": -1.49,
      "ret_5d": -0.64,
      "ret_20d": -3.84
    },
    {
      "date": "2011-03-04",
      "distance": 2.66,
      "close": 2359.96,
      "vix": 19.06,
      "ret_1d": -1.35,
      "ret_5d": -2.57,
      "ret_20d": -0.72
    },
    {
      "date": "2008-06-02",
      "distance": 2.7,
      "close": 2006.84,
      "vix": 19.83,
      "ret_1d": -0.5,
      "ret_5d": -1.35,
      "ret_20d": -8.46
    },
    {
      "date": "2025-11-12",
      "distance": 2.71,
      "close": 25517.33,
      "vix": 17.51,
      "ret_1d": -2.05,
      "ret_5d": -3.44,
      "ret_20d": 0.66
    },
    {
      "date": "2025-11-25",
      "distance": 2.76,
      "close": 25018.36,
      "vix": 18.56,
      "ret_1d": 0.87,
      "ret_5d": 2.35,
      "ret_20d": 2.55
    },
    {
      "date": "2021-12-22",
      "distance": 2.77,
      "close": 16180.14,
      "vix": 18.63,
      "ret_1d": 0.79,
      "ret_5d": 1.54,
      "ret_20d": -10.76
    }
  ]
}